rttapi/__init__.py
rttapi/api.py
rttapi/model.py
rttapi/parser.py
test/__init__.py
test/test_parser.py
rttapi-0.1.0.dist-info/LICENSE
rttapi-0.1.0.dist-info/METADATA
rttapi-0.1.0.dist-info/WHEEL
rttapi-0.1.0.dist-info/top_level.txt
rttapi-0.1.0.dist-info/RECORD
