Metadata-Version: 2.1
Name: rttapi
Version: 0.1.0
Summary: Python wrapper for the Realtime Trains API
Home-page: UNKNOWN
Author: Michael Dodd
License: MIT
Platform: UNKNOWN
